ankiapi/__init__.py
ankiapi/anki_api.py
ankiapi-0.1.0.dist-info/licenses/LICENSE
src/__init__.py
src/anki_api.py
ankiapi-0.1.0.dist-info/METADATA
ankiapi-0.1.0.dist-info/WHEEL
ankiapi-0.1.0.dist-info/top_level.txt
ankiapi-0.1.0.dist-info/RECORD
